MANIFEST.in
README.rst
gpds.py
setup.cfg
setup.py
gpds.egg-info/PKG-INFO
gpds.egg-info/SOURCES.txt
gpds.egg-info/dependency_links.txt
gpds.egg-info/entry_points.txt
gpds.egg-info/requires.txt
gpds.egg-info/top_level.txt