Metadata-Version: 1.1
Name: gpds
Version: 0.4.0
Summary: Simple GET-PUT-DELETE service to (temporary) store your files as an alternative to NFS shared folders.
Home-page: https://github.com/rembish/gpds
Author: Alex Rembish
Author-email: alex@rembish.org
License: BSD
Platform: UNKNOWN
Classifier: Development Status :: 4 - Beta
Classifier: License :: OSI Approved :: BSD License
Classifier: Operating System :: POSIX
Classifier: Programming Language :: Python
Classifier: Programming Language :: Python :: 2
Classifier: Programming Language :: Python :: 2.6
Classifier: Programming Language :: Python :: 2.7
Classifier: Topic :: Internet
Classifier: Topic :: Internet :: WWW/HTTP
Classifier: Topic :: Internet :: WWW/HTTP :: WSGI
Classifier: Topic :: Internet :: WWW/HTTP :: WSGI :: Application
